eunomia_mcp/__init__.py
eunomia_mcp/bridge.py
eunomia_mcp/middleware.py
eunomia_mcp/schemas.py
eunomia_mcp/utils.py
eunomia_mcp/cli/__init__.py
eunomia_mcp/cli/main.py
eunomia_mcp/cli/utils.py
eunomia_mcp-0.3.10.dist-info/METADATA
eunomia_mcp-0.3.10.dist-info/WHEEL
eunomia_mcp-0.3.10.dist-info/entry_points.txt
eunomia_mcp-0.3.10.dist-info/RECORD
