Metadata-Version: 2.4
Name: eunomia-mcp
Version: 0.3.10
Summary: Eunomia MCP authorization middleware
Author-email: What About You team <info@whataboutyou.ai>
License-Expression: Apache-2.0
Requires-Python: >=3.10
Requires-Dist: eunomia-ai>=0.3.10
Requires-Dist: eunomia-sdk>=0.3.10
Requires-Dist: fastmcp>=2.10.4
Requires-Dist: pydantic>=2.11.7
Requires-Dist: typer>=0.15.2
